flask_minijson.py
flask_minijson-0.4.dist-info/LICENSE
flask_minijson-0.4.dist-info/METADATA
flask_minijson-0.4.dist-info/WHEEL
flask_minijson-0.4.dist-info/top_level.txt
flask_minijson-0.4.dist-info/RECORD
