Metadata-Version: 2.1
Name: flask-minijson
Version: 0.4
Summary: A Flask extension to allow client's to submit data using the MiniJSON codec
Home-page: https://github.com/Dronehub/flask-minijson
Author: Piotr Maślanka
Author-email: pmaslanka@smok.co
Project-URL: Code, https://github.com/Dronehub/flask-minijson
Project-URL: Issue tracker, https://github.com/Dronehub/flask-minijson/issues
Classifier: Development Status :: 4 - Beta
Classifier: Programming Language :: Python
Classifier: Programming Language :: Python :: 3.5
Classifier: Programming Language :: Python :: 3.6
Classifier: Programming Language :: Python :: 3.7
Classifier: Programming Language :: Python :: 3.8
Classifier: Programming Language :: Python :: 3.9
Classifier: Programming Language :: Python :: Implementation :: CPython
Classifier: Programming Language :: Python :: Implementation :: PyPy
Classifier: Operating System :: OS Independent
Classifier: License :: OSI Approved :: MIT License
Classifier: Topic :: Software Development :: Libraries
Requires-Python: !=2.7.*,!=3.0.*,!=3.1.*,!=3.2.*,!=3.3.*,!=3.4.*
License-File: LICENSE
